[{"name": "open_meteo", "status": "ok", "fetched_at": "2026-05-02T07:01:56.139882Z", "age": "just now"}, {"name": "yr_no", "status": "ok", "fetched_at": "2026-05-02T07:01:58.191619Z", "age": "just now"}, {"name": "snow_forecast", "status": "ok", "fetched_at": "2026-05-02T07:01:59.537602Z", "age": "just now"}, {"name": "mountain_forecast", "status": "ok", "fetched_at": "2026-05-02T07:02:01.242712Z", "age": "just now"}, {"name": "open_meteo_ensemble", "status": "ok", "fetched_at": "2026-05-02T07:02:01.699666Z", "age": "just now"}, {"name": "seasonal", "status": "ok", "fetched_at": "2026-05-02T07:02:03.069386Z", "age": "just now"}, {"name": "rainviewer", "status": "ok", "fetched_at": "2026-05-02T07:02:03.528938Z", "age": "just now"}]