[{"name": "open_meteo", "status": "ok", "fetched_at": "2026-05-06T07:36:37.686252Z", "age": "just now"}, {"name": "yr_no", "status": "ok", "fetched_at": "2026-05-06T07:36:39.005760Z", "age": "just now"}, {"name": "snow_forecast", "status": "ok", "fetched_at": "2026-05-06T07:36:39.939584Z", "age": "just now"}, {"name": "mountain_forecast", "status": "ok", "fetched_at": "2026-05-06T07:36:41.479158Z", "age": "just now"}, {"name": "open_meteo_ensemble", "status": "ok", "fetched_at": "2026-05-06T07:36:41.932494Z", "age": "just now"}, {"name": "seasonal", "status": "ok", "fetched_at": "2026-05-06T07:36:42.867528Z", "age": "just now"}, {"name": "rainviewer", "status": "ok", "fetched_at": "2026-05-06T07:36:43.337846Z", "age": "just now"}]