[{"name": "open_meteo", "status": "ok", "fetched_at": "2026-03-09T06:00:21.261235Z", "age": "just now"}, {"name": "yr_no", "status": "ok", "fetched_at": "2026-03-09T06:00:38.444680Z", "age": "just now"}, {"name": "snow_forecast", "status": "ok", "fetched_at": "2026-03-09T06:00:39.921472Z", "age": "just now"}, {"name": "mountain_forecast", "status": "ok", "fetched_at": "2026-03-09T06:00:42.123974Z", "age": "just now"}, {"name": "open_meteo_ensemble", "status": "ok", "fetched_at": "2026-03-09T06:00:42.528377Z", "age": "just now"}]