[{"name": "open_meteo", "status": "ok", "fetched_at": "2026-03-23T11:46:57.100101Z", "age": "just now"}, {"name": "yr_no", "status": "ok", "fetched_at": "2026-03-23T11:46:58.359282Z", "age": "just now"}, {"name": "snow_forecast", "status": "ok", "fetched_at": "2026-03-23T11:46:59.628109Z", "age": "just now"}, {"name": "mountain_forecast", "status": "ok", "fetched_at": "2026-03-23T11:47:00.907841Z", "age": "just now"}, {"name": "open_meteo_ensemble", "status": "ok", "fetched_at": "2026-03-23T11:47:01.240952Z", "age": "just now"}]