[{"name": "open_meteo", "status": "ok", "fetched_at": "2026-02-27T17:38:33.847318Z", "age": "just now"}, {"name": "yr_no", "status": "ok", "fetched_at": "2026-02-27T17:38:35.121452Z", "age": "just now"}, {"name": "snow_forecast", "status": "ok", "fetched_at": "2026-02-27T17:38:36.448480Z", "age": "just now"}, {"name": "mountain_forecast", "status": "ok", "fetched_at": "2026-02-27T17:38:38.091549Z", "age": "just now"}, {"name": "open_meteo_ensemble", "status": "ok", "fetched_at": "2026-02-27T17:38:38.438055Z", "age": "just now"}]