{
  "icon_seamless.snowfall": {
    "x": -0.004608,
    "P": 0.095127,
    "n_updates": 198,
    "initialized_from": "ewma"
  },
  "ecmwf_ifs025.snowfall": {
    "x": 0.100712,
    "P": 0.095127,
    "n_updates": 198,
    "initialized_from": "ewma"
  },
  "gfs_seamless.snowfall": {
    "x": -0.006227,
    "P": 0.095127,
    "n_updates": 198,
    "initialized_from": "ewma"
  },
  "arpege_seamless.snowfall": {
    "x": 0.145693,
    "P": 0.095127,
    "n_updates": 198,
    "initialized_from": "ewma"
  },
  "ukmo_seamless.snowfall": {
    "x": -0.00717,
    "P": 0.095127,
    "n_updates": 198,
    "initialized_from": "ewma"
  },
  "ecmwf_aifs025_single.snowfall": {
    "x": -0.006004,
    "P": 0.095127,
    "n_updates": 198
  },
  "gfs_graphcast025.snowfall": {
    "x": 2.070752,
    "P": 0.095127,
    "n_updates": 198
  },
  "composite.rain": {
    "x": -0.334523,
    "P": 0.095127,
    "n_updates": 198
  }
}