{
  "updated_at": "2026-03-25T11:43:58.993181Z",
  "weights": {
    "icon_seamless": 0.1917,
    "ecmwf_ifs025": 0.2694,
    "gfs_seamless": 0.2371,
    "arpege_seamless": 0.0997,
    "ukmo_seamless": 0.2021
  },
  "bias_corrections": {
    "icon_seamless": {
      "snowfall": 1.2633
    },
    "ecmwf_ifs025": {
      "snowfall": 0.5694
    },
    "gfs_seamless": {
      "snowfall": 0.1098
    },
    "arpege_seamless": {
      "snowfall": 2.7188
    },
    "ukmo_seamless": {
      "snowfall": 0.8181
    }
  },
  "ewma_mae": {
    "icon_seamless": {
      "snowfall": 1.2427596397390654,
      "temperature": null
    },
    "ecmwf_ifs025": {
      "snowfall": 0.8841282827943729,
      "temperature": null
    },
    "gfs_seamless": {
      "snowfall": 1.0048570676721158,
      "temperature": null
    },
    "arpege_seamless": {
      "snowfall": 2.4537182116027396,
      "temperature": null
    },
    "ukmo_seamless": {
      "snowfall": 1.1788858715392336,
      "temperature": null
    }
  }
}