{
  "updated_at": "2026-03-22T05:56:06.690539Z",
  "weights": {
    "icon_seamless": 0.1678,
    "ecmwf_ifs025": 0.3238,
    "gfs_seamless": 0.1943,
    "arpege_seamless": 0.103,
    "ukmo_seamless": 0.2111
  },
  "bias_corrections": {
    "icon_seamless": {
      "snowfall": 1.3195
    },
    "ecmwf_ifs025": {
      "snowfall": 0.4095
    },
    "gfs_seamless": {
      "snowfall": 0.2925
    },
    "arpege_seamless": {
      "snowfall": 2.6893
    },
    "ukmo_seamless": {
      "snowfall": 1.4586
    }
  },
  "ewma_mae": {
    "icon_seamless": {
      "snowfall": 0.7148420170418938,
      "temperature": null
    },
    "ecmwf_ifs025": {
      "snowfall": 0.370337303622441,
      "temperature": null
    },
    "gfs_seamless": {
      "snowfall": 0.6171406545254754,
      "temperature": null
    },
    "arpege_seamless": {
      "snowfall": 1.1641762055297473,
      "temperature": null
    },
    "ukmo_seamless": {
      "snowfall": 0.5681952242191808,
      "temperature": null
    }
  }
}