{
  "updated_at": "2026-04-22T06:57:33.734501Z",
  "n_verifications": 162,
  "per_model": {
    "icon_seamless": {
      "snowfall": {
        "bias": 0.0036,
        "mae": 0.1206,
        "rmse": 0.1762,
        "n_samples": 477
      }
    },
    "ecmwf_ifs025": {
      "snowfall": {
        "bias": 0.1814,
        "mae": 0.3077,
        "rmse": 0.5121,
        "n_samples": 477
      }
    },
    "gfs_seamless": {
      "snowfall": {
        "bias": -0.0437,
        "mae": 0.1185,
        "rmse": 0.1888,
        "n_samples": 477
      }
    },
    "arpege_seamless": {
      "snowfall": {
        "bias": 0.3694,
        "mae": 0.3816,
        "rmse": 0.5814,
        "n_samples": 477
      }
    },
    "ukmo_seamless": {
      "snowfall": {
        "bias": -0.0975,
        "mae": 0.1103,
        "rmse": 0.1711,
        "n_samples": 477
      }
    }
  },
  "overall": {
    "snowfall": {
      "bias": 0.3049,
      "mae": 0.4005,
      "rmse": 0.4755,
      "n_samples": 477
    },
    "temperature": {
      "bias": 0.676,
      "mae": 1.748,
      "rmse": 2.0969,
      "n_samples": 477
    },
    "wind": {
      "bias": 6.7384,
      "mae": 6.7384,
      "rmse": 7.5662,
      "n_samples": 477
    },
    "rain": {
      "bias": -0.1958,
      "mae": 0.3608,
      "rmse": 0.5207,
      "n_samples": 201
    },
    "temperature_min": {
      "bias": 3.4161,
      "mae": 3.4177,
      "rmse": 3.5177,
      "n_samples": 201
    },
    "wind_gust": {
      "bias": 6.6168,
      "mae": 11.0939,
      "rmse": 12.8079,
      "n_samples": 201
    }
  },
  "powder_accuracy": {
    "hit_rate": 0.0021,
    "false_alarm_rate": 0.0,
    "miss_rate": 0.0,
    "correct_negative_rate": 0.998,
    "n_days": 477
  },
  "last_verified_dates": [
    "2026-03-21",
    "2026-03-22",
    "2026-03-23",
    "2026-03-24",
    "2026-03-25",
    "2026-03-26",
    "2026-03-27",
    "2026-03-28",
    "2026-03-29",
    "2026-03-30",
    "2026-03-31",
    "2026-04-01",
    "2026-04-02",
    "2026-04-03",
    "2026-04-04",
    "2026-04-05",
    "2026-04-06",
    "2026-04-07",
    "2026-04-08",
    "2026-04-09",
    "2026-04-10",
    "2026-04-11",
    "2026-04-12",
    "2026-04-13",
    "2026-04-14",
    "2026-04-15",
    "2026-04-16",
    "2026-04-17",
    "2026-04-18",
    "2026-04-19"
  ]
}