{
  "updated_at": "2026-02-27T11:35:04.047675Z",
  "n_verifications": 2,
  "per_model": {
    "icon_seamless": {
      "snowfall": {
        "bias": 0.84,
        "mae": 0.84,
        "rmse": 0.84,
        "n_samples": 2
      }
    },
    "ecmwf_ifs025": {
      "snowfall": {
        "bias": -0.21,
        "mae": 0.21,
        "rmse": 0.21,
        "n_samples": 2
      }
    },
    "gfs_seamless": {
      "snowfall": {
        "bias": -0.63,
        "mae": 0.63,
        "rmse": 0.63,
        "n_samples": 2
      }
    },
    "arpege_seamless": {
      "snowfall": {
        "bias": 1.4,
        "mae": 1.4,
        "rmse": 1.4,
        "n_samples": 2
      }
    },
    "ukmo_seamless": {
      "snowfall": {
        "bias": 0.21,
        "mae": 0.21,
        "rmse": 0.21,
        "n_samples": 2
      }
    }
  },
  "overall": {
    "snowfall": {
      "bias": 0.03,
      "mae": 0.03,
      "rmse": 0.03,
      "n_samples": 2
    },
    "temperature": {
      "bias": 1.4,
      "mae": 1.4,
      "rmse": 1.4,
      "n_samples": 2
    },
    "wind": {
      "bias": 20.2,
      "mae": 20.2,
      "rmse": 20.2,
      "n_samples": 2
    }
  },
  "powder_accuracy": {
    "hit_rate": 0.0,
    "false_alarm_rate": 0.0,
    "miss_rate": 0.0,
    "correct_negative_rate": 1.0,
    "n_days": 2
  },
  "last_verified_dates": [
    "2026-02-24"
  ]
}